fairdo/__about__.py
fairdo/__init__.py
fairdo/metrics/__init__.py
fairdo/metrics/dataset.py
fairdo/metrics/dependence.py
fairdo/metrics/group.py
fairdo/metrics/independence.py
fairdo/metrics/individual.py
fairdo/metrics/penalty.py
fairdo/metrics/prediction.py
fairdo/optimize/__init__.py
fairdo/optimize/baseline.py
fairdo/optimize/geneticalgorithm.py
fairdo/optimize/geneticoperators/__init__.py
fairdo/optimize/geneticoperators/crossover.py
fairdo/optimize/geneticoperators/mutation.py
fairdo/optimize/geneticoperators/selection.py
fairdo/optimize/multi/__init__.py
fairdo/optimize/multi/nsga.py
fairdo/optimize/operators/__init__.py
fairdo/optimize/operators/crossover.py
fairdo/optimize/operators/initialization.py
fairdo/optimize/operators/mutation.py
fairdo/optimize/operators/selection.py
fairdo/optimize/single/__init__.py
fairdo/optimize/single/baseline.py
fairdo/optimize/single/ga.py
fairdo/preprocessing/__init__.py
fairdo/preprocessing/_unawareness.py
fairdo/preprocessing/_uniform.py
fairdo/preprocessing/base.py
fairdo/preprocessing/metricoptimizer.py
fairdo/preprocessing/solverwrapper.py
fairdo/preprocessing/wrapper.py
fairdo/utils/__init__.py
fairdo/utils/dataset.py
fairdo/utils/helper.py
fairdo/utils/math.py
fairdo/utils/penalty.py
fairdo-0.1.10.dist-info/LICENSE
fairdo-0.1.10.dist-info/METADATA
fairdo-0.1.10.dist-info/WHEEL
fairdo-0.1.10.dist-info/top_level.txt
fairdo-0.1.10.dist-info/RECORD
