Metadata-Version: 2.1
Name: fairdo
Version: 0.1.10
Summary: Fairness-Agnostic Data Optimization
Home-page: https://fairdo.readthedocs.io/en/latest/
Author: Manh Khoi Duong
Author-email: duong@hhu.de
License: MIT License
Project-URL: Source Code, https://github.com/mkduong-ai/fairdo
Classifier: Programming Language :: Python :: 3
Classifier: License :: OSI Approved :: MIT License
Classifier: Operating System :: OS Independent
Requires-Python: <3.9,>=3.8
License-File: LICENSE
Requires-Dist: numpy ==1.22.1
Requires-Dist: pandas ==1.4.2
Requires-Dist: scikit-learn ==1.1.3
Requires-Dist: scipy ==1.7.3
Requires-Dist: pathos >=0.3.1
Requires-Dist: wheel >=0.35.0
Requires-Dist: requests ==2.28.1
Requires-Dist: matplotlib ==3.4.3
